.gitignore
.travis.yml
README.mdown
setup.py
mezzanine_agenda/__init__.py
mezzanine_agenda/admin.py
mezzanine_agenda/defaults.py
mezzanine_agenda/feeds.py
mezzanine_agenda/models.py
mezzanine_agenda/tests.py
mezzanine_agenda/urls.py
mezzanine_agenda/views.py
mezzanine_agenda.egg-info/PKG-INFO
mezzanine_agenda.egg-info/SOURCES.txt
mezzanine_agenda.egg-info/dependency_links.txt
mezzanine_agenda.egg-info/requires.txt
mezzanine_agenda.egg-info/top_level.txt
mezzanine_agenda/fixtures/events_page.json
mezzanine_agenda/templates/agenda/event_detail.html
mezzanine_agenda/templates/agenda/event_list.html
mezzanine_agenda/templates/agenda/includes/filter_panel.html
mezzanine_agenda/templatetags/__init__.py
mezzanine_agenda/templatetags/event_tags.py
test_project/__init__.py
test_project/local_settings.py
test_project/manage.py
test_project/settings.py
test_project/urls.py