Metadata-Version: 1.1
Name: mezzanine-agenda
Version: 0.1.1
Summary: Events for the Mezzanine CMS
Home-page: https://github.com/jpells/mezzanine-agenda
Author: James Pells
Author-email: jimmy@jamespells.com
License: UNKNOWN
Platform: UNKNOWN
Classifier: Development Status :: 4 - Beta
Classifier: Environment :: Web Environment
Classifier: Framework :: Django
Classifier: License :: OSI Approved :: MIT License
Classifier: Natural Language :: English
Classifier: Operating System :: OS Independent
Classifier: Topic :: Internet :: WWW/HTTP :: Dynamic Content
